felapps/__init__.py
felapps/apps/__init__.py
felapps/apps/appdrawer/__init__.py
felapps/apps/appdrawer/appdrawer.py
felapps/apps/cornalyzer/__init__.py
felapps/apps/cornalyzer/cornalyzer.py
felapps/apps/cornalyzer_old/__init__.py
felapps/apps/cornalyzer_old/cornalyzer.py
felapps/apps/dataworkshop/__init__.py
felapps/apps/dataworkshop/dataworkshop.py
felapps/apps/felformula/__init__.py
felapps/apps/felformula/felformula.py
felapps/apps/imageviewer/__init__.py
felapps/apps/imageviewer/imageviewer.py
felapps/apps/matchwizard/__init__.py
felapps/apps/matchwizard/matchwizard.py
felapps/apps/wxmpv/__init__.py
felapps/apps/wxmpv/wxmpv.py
felapps/facilities/__init__.py
felapps/facilities/dcls.py
felapps/physics/__init__.py
felapps/physics/felbase.py
felapps/physics/felcalc.py
felapps/utils/EnhancedStatusBar.py
felapps/utils/__init__.py
felapps/utils/analysisframe.py
felapps/utils/datascanapp.py
felapps/utils/datascanframe.py
felapps/utils/datascanframe_ui.py
felapps/utils/datautils.py
felapps/utils/felutils.py
felapps/utils/funclistframe.py
felapps/utils/funutils.py
felapps/utils/imageutils.py
felapps/utils/matchutils.py
felapps/utils/miscutils.py
felapps/utils/myui.py
felapps/utils/parseutils.py
felapps/utils/pltutils.py
felapps/utils/resutils.py
felapps/utils/scanutils.py
felapps/utils/uiutils.py
felapps-2.0.0.data/data/share/applications/felapps-appdrawer.desktop
felapps-2.0.0.data/data/share/applications/felapps-apps.directory
felapps-2.0.0.data/data/share/applications/felapps-cornalyzer.desktop
felapps-2.0.0.data/data/share/applications/felapps-dataworkshop.desktop
felapps-2.0.0.data/data/share/applications/felapps-felformula.desktop
felapps-2.0.0.data/data/share/applications/felapps-imageviewer.desktop
felapps-2.0.0.data/data/share/applications/felapps-latticeviewer.desktop
felapps-2.0.0.data/data/share/applications/felapps-wxmpv.desktop
felapps-2.0.0.data/data/share/felapps/imageviewer.xml
felapps-2.0.0.dist-info/DESCRIPTION.rst
felapps-2.0.0.dist-info/METADATA
felapps-2.0.0.dist-info/RECORD
felapps-2.0.0.dist-info/WHEEL
felapps-2.0.0.dist-info/metadata.json
felapps-2.0.0.dist-info/top_level.txt
