Metadata-Version: 2.0
Name: felapps
Version: 2.0.0
Summary: High-level applications for FEL commissioning.
Home-page: http://archman.github.io/felapps/
Author: Tong Zhang
Author-email: zhangtong@sinap.ac.cn
License: MIT
Keywords: FEL HLA high-level python wxpython
Platform: Linux
Classifier: Programming Language :: Python
Classifier: Topic :: Software Development :: Libraries :: Python Modules
Classifier: Topic :: Scientific/Engineering :: Physics
